{"v":"5.6.6","ip":0,"op":149,"fr":60,"w":288,"h":288,"layers":[{"ind":7,"nm":"surface1","ao":0,"ip":0,"op":720,"st":0,"ty":4,"ks":{"o":{"a":1,"k":[{"i":{"x":[0.67],"y":[1]},"o":{"x":[0.33],"y":[0]},"t":12,"s":[0]},{"t":29,"s":[100]}],"ix":11},"r":{"a":0,"k":0,"ix":10},"p":{"a":1,"k":[{"i":{"x":0.67,"y":1},"o":{"x":0.33,"y":0},"t":0,"s":[-187,180],"to":[74,0,0],"ti":[-74,0,0]},{"t":29,"s":[180,180]}],"ix":2},"a":{"a":0,"k":[144,144],"ix":1},"s":{"a":1,"k":[{"i":{"x":[0.67,0.67,0.67],"y":[1,1,1]},"o":{"x":[0.33,0.33,0.33],"y":[0,0,0]},"t":29,"s":[79,79,100]},{"t":51,"s":[106,106,100]}],"ix":6}},"shapes":[{"ty":"gr","hd":false,"nm":"surface1","it":[{"ty":"gr","hd":false,"it":[{"ty":"sh","ks":{"k":{"i":[[0,0],[0,0],[0,0],[0,0],[0,0],[0,0],[0,0],[0,0],[0,0],[0,0],[0,0]],"o":[[0,0],[0,0],[0,0],[0,0],[0,0],[0,0],[0,0],[0,0],[0,0],[0,0],[0,0]],"v":[[27.24,63.23],[169.05,63.06],[152.7,87.08],[76.95,87.08],[82.85,95.08],[148.24,95.08],[132.23,117.33],[97.77,117.33],[116.22,140.25],[98.86,164.6],[27.23,63.23]],"c":true}}},{"ty":"fl","o":{"k":100},"c":{"k":[0.37,0.51,0.75,1]}},{"ty":"tr","o":{"k":100},"r":{"k":0},"p":{"k":[0,0]},"a":{"k":[0,0]},"s":{"k":[100,100]},"sk":{"k":0},"sa":{"k":0},"hd":false}]},{"ty":"gr","hd":false,"it":[{"ty":"sh","ks":{"k":{"i":[[0,0],[0,0],[0,0],[0,0],[0,0],[0,0],[0,0],[0,0],[0,0],[0,0]],"o":[[0,0],[0,0],[0,0],[0,0],[0,0],[0,0],[0,0],[0,0],[0,0],[0,0]],"v":[[28.08,63.57],[182.28,63.06],[167.7,86.74],[92.54,86.74],[98.1,95.08],[160.04,95.08],[145.46,117.32],[111.33,117.33],[129.45,141.68],[105.77,175.05]],"c":true}}},{"ty":"fl","o":{"k":100},"c":{"k":[0.73,0.74,0.75,1]}},{"ty":"tr","o":{"k":100},"r":{"k":0},"p":{"k":[0,0]},"a":{"k":[0,0]},"s":{"k":[100,100]},"sk":{"k":0},"sa":{"k":0},"hd":false}]},{"ty":"gr","hd":false,"it":[{"ty":"rc","s":{"k":[216,216]},"p":{"k":[108,108]},"r":{"k":0}},{"ty":"fl","o":{"k":100},"c":{"k":[1,1,1,1]}},{"ty":"tr","o":{"k":100},"r":{"k":0},"p":{"k":[0,0]},"a":{"k":[0,0]},"s":{"k":[100,100]},"sk":{"k":0},"sa":{"k":0},"hd":false}]},{"ty":"tr","o":{"k":100},"r":{"k":0},"p":{"k":[0,0]},"a":{"k":[0,0]},"s":{"k":[100,100]},"sk":{"k":0},"sa":{"k":0},"hd":false}]}]}],"meta":{"g":"LF SVG to Lottie"}}